db0905/__init__.py
db0905/builder.py
db0905/consts.py
db0905/parser.py
db0905/utils.py
demo/__init__.py
demo/dump.py
demo/load.py
tests/__init__.py
tests/test_builder.py
tests/test_parser.py
db0905-1.0.1.dist-info/LICENSE
db0905-1.0.1.dist-info/METADATA
db0905-1.0.1.dist-info/WHEEL
db0905-1.0.1.dist-info/top_level.txt
db0905-1.0.1.dist-info/RECORD
